MANIFEST.in
README.txt
setup.py
collective/__init__.py
collective.improvedbyline.egg-info/PKG-INFO
collective.improvedbyline.egg-info/SOURCES.txt
collective.improvedbyline.egg-info/dependency_links.txt
collective.improvedbyline.egg-info/entry_points.txt
collective.improvedbyline.egg-info/namespace_packages.txt
collective.improvedbyline.egg-info/not-zip-safe
collective.improvedbyline.egg-info/requires.txt
collective.improvedbyline.egg-info/top_level.txt
collective/improvedbyline/__init__.py
collective/improvedbyline/browser.zcml
collective/improvedbyline/configure.zcml
collective/improvedbyline/document_byline.pt
collective/improvedbyline/interfaces.py
collective/improvedbyline/viewlet.py
collective/improvedbyline/profiles/default/browserlayer.xml
collective/improvedbyline/profiles/default/metadata.xml
collective/improvedbyline/tests/__init__.py
collective/improvedbyline/tests/test_byline.py
docs/HISTORY.txt
docs/INSTALL.txt
docs/LICENSE.GPL
docs/LICENSE.txt