Metadata-Version: 1.0
Name: collective.improvedbyline
Version: 1.1
Summary: Extends byline viewlet with Publication Date.
Home-page: http://svn.plone.org/svn/collective/collective.improvedbyline
Author: Vitaliy Podoba
Author-email: vitaliypodoba@gmail.com
License: GPL
Keywords: plone viewlet byline publication date
Platform: UNKNOWN
Classifier: Framework :: Plone
Classifier: Programming Language :: Python
